Blauwal3_SingleCell-1.7.2-py3.10-nspkg.pth
orangecontrib/single_cell/__init__.py
orangecontrib/single_cell/i18n_config.py
orangecontrib/single_cell/reader.py
orangecontrib/single_cell/locale/single_cell.de.yml
orangecontrib/single_cell/locale/single_cell.en.yml
orangecontrib/single_cell/locale/single_cell.zh.yml
orangecontrib/single_cell/preprocess/__init__.py
orangecontrib/single_cell/preprocess/alignment.py
orangecontrib/single_cell/preprocess/biweight.py
orangecontrib/single_cell/preprocess/cca.py
orangecontrib/single_cell/preprocess/clusteranalysis.py
orangecontrib/single_cell/preprocess/scbnorm.py
orangecontrib/single_cell/preprocess/scpreprocess.py
orangecontrib/single_cell/preprocess/data/bone_marrow_louvain.pickle
orangecontrib/single_cell/tests/__init__.py
orangecontrib/single_cell/tests/test_load_data.py
orangecontrib/single_cell/tests/test_owaligndatasets.py
orangecontrib/single_cell/tests/test_owbatchnorm.py
orangecontrib/single_cell/tests/test_owdatasets.py
orangecontrib/single_cell/tests/test_owdotmatrix.py
orangecontrib/single_cell/tests/test_owdropout.py
orangecontrib/single_cell/tests/test_owfilter.py
orangecontrib/single_cell/tests/test_owgenerank.py
orangecontrib/single_cell/tests/test_owloaddata.py
orangecontrib/single_cell/tests/test_owmultisample.py
orangecontrib/single_cell/tests/test_owscorecells.py
orangecontrib/single_cell/tests/test_owscoregenes.py
orangecontrib/single_cell/tests/test_owscpreprocess.py
orangecontrib/single_cell/tests/test_owspatialautocorrelation.py
orangecontrib/single_cell/tests/data/DATA_MATRIX_LOG_TPM.txt
orangecontrib/single_cell/tests/data/data.csv
orangecontrib/single_cell/tests/data/data.loom
orangecontrib/single_cell/tests/data/data.pkl
orangecontrib/single_cell/tests/data/data.txt.gz
orangecontrib/single_cell/tests/data/data.xls
orangecontrib/single_cell/tests/data/data.xlsx
orangecontrib/single_cell/tests/data/data_dense.h5ad
orangecontrib/single_cell/tests/data/data_sparse.h5ad
Blauwal3_SingleCell-1.7.2.dist-info/LICENSE
Blauwal3_SingleCell-1.7.2.dist-info/METADATA
Blauwal3_SingleCell-1.7.2.dist-info/WHEEL
Blauwal3_SingleCell-1.7.2.dist-info/entry_points.txt
Blauwal3_SingleCell-1.7.2.dist-info/namespace_packages.txt
Blauwal3_SingleCell-1.7.2.dist-info/top_level.txt
Blauwal3_SingleCell-1.7.2.dist-info/RECORD
